drf_chat/__init__.py
drf_chat/admin.py
drf_chat/apps.py
drf_chat/consumers.py
drf_chat/exceptions.py
drf_chat/models.py
drf_chat/routing.py
drf_chat/serializers.py
drf_chat/signals.py
drf_chat/tests.py
drf_chat/token_auth.py
drf_chat/urls.py
drf_chat/utils.py
drf_chat/validators.py
drf_chat/views.py
drf_chat/migrations/0001_initial.py
drf_chat/migrations/__init__.py
drf_chat-1.0.0.dist-info/LICENSE.txt
drf_chat-1.0.0.dist-info/METADATA
drf_chat-1.0.0.dist-info/WHEEL
drf_chat-1.0.0.dist-info/top_level.txt
drf_chat-1.0.0.dist-info/RECORD
