Metadata-Version: 2.1
Name: drf-chat
Version: 1.0.0
Summary: UNKNOWN
Home-page: https://github.com/null-none/drf-chat
Author: Kalinin Mitko
Author-email: kalinin.mitko@gmail.com
License: UNKNOWN
Platform: UNKNOWN
License-File: LICENSE.txt
Requires-Dist: channels
Requires-Dist: redis
Requires-Dist: channels-redis
